LICENSE
MANIFEST.in
README.md
requirements.txt
setup.py
./natscript/__init__.py
./natscript/__main__.py
./natscript/cli.py
./natscript/interpret.py
./natscript/internal/__init__.py
./natscript/internal/exceptions.py
./natscript/internal/interfaces.py
./natscript/internal/interpreter.py
./natscript/internal/lexer.py
./natscript/internal/parsing.py
./natscript/internal/token_.py
./natscript/internal/tokenvalue.py
./natscript/tokens_/__init__.py
./natscript/tokens_/compiler.py
./natscript/tokens_/tokens.py
./natscript/util/__init__.py
./natscript/util/path.py
./natscript/util/pattern_matching.py
doc/README.md
doc/language_reference.md
natscript/py.typed
natscript.egg-info/PKG-INFO
natscript.egg-info/SOURCES.txt
natscript.egg-info/dependency_links.txt
natscript.egg-info/not-zip-safe
natscript.egg-info/top_level.txt