Metadata-Version: 2.1
Name: natscript
Version: 0.1.0
Summary: Natscript interpreter
Home-page: https://github.com/rbaltrusch/natscript
Author: Richard Baltrusch
License: MIT
Keywords: python
Platform: UNKNOWN
Classifier: Development Status :: 4 - Beta
Classifier: Environment :: Console
Classifier: Intended Audience :: Developers
Classifier: License :: OSI Approved :: MIT License
Classifier: Programming Language :: Python
Classifier: Programming Language :: Python :: 3
Classifier: Programming Language :: Python :: 3 :: Only
Classifier: Programming Language :: Python :: 3.8
Classifier: Programming Language :: Python :: 3.9
Classifier: Programming Language :: Python :: 3.10
Classifier: Topic :: Software Development
Classifier: Topic :: Software Development :: Interpreters
Classifier: Typing :: Typed
Requires-Python: >=3.8
